{
    "daily": [
        {
            "dt": "2025-04-08",
            "temp": {
                "avg": 23.585000000000008,
                "min": 21.100000000000023,
                "max": 26.0
            }
        },
        {
            "dt": "2025-04-09",
            "temp": {
                "avg": 25.170000000000037,
                "min": 22.200000000000045,
                "max": 29.57000000000005
            }
        },
        {
            "dt": "2025-04-10",
            "temp": {
                "avg": 26.945000000000014,
                "min": 22.970000000000027,
                "max": 33.700000000000045
            }
        },
        {
            "dt": "2025-04-11",
            "temp": {
                "avg": 25.67750000000003,
                "min": 23.210000000000036,
                "max": 32.460000000000036
            }
        },
        {
            "dt": "2025-04-12",
            "temp": {
                "avg": 24.18000000000002,
                "min": 20.470000000000027,
                "max": 27.760000000000048
            }
        },
        {
            "dt": "2025-04-13",
            "temp": {
                "avg": 22.325000000000017,
                "min": 20.590000000000032,
                "max": 24.060000000000002
            }
        }
    ]
}